{
  "vendor/tools/backpack": {
    "url": "https://github.com/realityforge/backpack.git",
    "branch": "master",
    "revision": "fa6e1781483503569d3c5b922363dbb1abc63956"
  },
  "vendor/tools/kinjen": {
    "url": "https://github.com/realityforge/kinjen.git",
    "branch": "master",
    "revision": "5cb65e4abf3711824c2da381a1d05ccdadbe1daa"
  },
  "vendor/tools/zim": {
    "url": "https://github.com/realityforge/zim.git",
    "branch": "master",
    "revision": "6125e8f2de172b9d8b9de37b37c52fa9138a98b3"
  }
}
